Workbook

Sheet Transactions
A1: Date | B1: Type | C1: Category | D1: Description | E1: Amount | F1: Payment Method | G1: Notes
A2: 46127 | B2: Income | C2: Salary | D2: Salary | E2: 6512.67 | F2: GIRO
A3: 46127 | B3: Expense | C3: Subscription | D3: Prime | E3: 4.999 | F3: Credit Card | G3: Citi Cash+
A4: 46130 | B4: Expense | C4: Shopping | D4: Shoppee | E4: 6.58 | F4: Credit Card | G4: Citi Cash+
A5: 46131 | B5: Expense | C5: Shopping | D5: Shoppee | E5: 5.46 | F5: Credit Card | G5: Citi Cash+
A6: 46127 | B6: Expense | C6: Shopping | D6: Tiktok | E6: 6.54 | F6: Credit Card | G6: Citi Rewards
A7: 46128 | B7: Expense | C7: Food | D7: Chicken Rice | E7: 6 | F7: Credit Card | G7: Citi Rewards
A8: 46127 | B8: Expense | C8: Transport | D8: Bus | E8: 0.1 | F8: Credit Card | G8: Citi Rewards
A9: 46129 | B9: Expense | C9: Food | D9: Chicken Rice | E9: 8.1 | F9: Credit Card | G9: Citi Rewards
A10: 46130 | B10: Expense | C10: Shopping | D10: Amazon Cookie | E10: 16.5 | F10: Credit Card | G10: Citi Rewards
A11: 46130 | B11: Expense | C11: Subscription | D11: iCloud | E11: 13.98 | F11: Credit Card | G11: Citi Rewards
A12: 46130 | B12: Expense | C12: Grocery | D12: Fairprice | E12: 25.88 | F12: Credit Card | G12: Citi Rewards
A13: 46131 | B13: Expense | C13: Entertainment | D13: Pokemon Card | E13: 18 | F13: Credit Card | G13: Citi Rewards
A14: 46129 | B14: Expense | C14: Subscription | D14: Spotify | E14: 17.46 | F14: Debit Card | G14: DBS
... A16: 46131 | B16: Expense | C16: Food | D16: Popeye | E16: 13.7 | F16: Credit Card | G16: Yuu
A17: 46127 | B17: Income | C17: Gift | D17: Tamil New Year | E17: 200 | F17: Cash
A18: 46127 | B18: Income | C18: Misc | D18: Dental Refund | E18: 20 | F18: Cash
A19: 46131 | B19: Expense | C19: Food | D19: Subway | E19: 13 | F19: Credit Card | G19: Citi Rewards
A20: 46132 | B20: Expense | C20: Food | D20: Chicken Rice | E20: 7.1 | F20: Credit Card | G20: Citi Rewards
A21: 46132 | B21: Expense | C21: Transport | D21: Bus | E21: 0.2 | F21: Credit Card | G21: Citi Rewards
A22: 46132 | B22: Expense | C22: Grocery | D22: Fairprice | E22: 14.44 | F22: Credit Card | G22: Citi Rewards
A23: 46132 | B23: Expense | C23: Grocery | D23: Fairprice | E23: 18.27 | F23: Credit Card | G23: Citi Rewards
A24: 46134 | B24: Expense | C24: Food | D24: Chicken Rice | E24: 5.4 | F24: Credit Card | G24: Citi Rewards
A25: 46134 | B25: Expense | C25: Food | D25: Siew Mai | E25: 5.1 | F25: Credit Card | G25: Citi Rewards
A26: 46134 | B26: Expense | C26: Grocery | D26: Fairprice | E26: 3.1 | F26: Credit Card | G26: Citi Rewards
A27: 46135 | B27: Expense | C27: Transport | D27: Bus | E27: 0.2 | F27: Credit Card | G27: Citi Rewards
A28: 46136 | B28: Expense | C28: Food | D28: Stuffd | E28: 15.1 | F28: Credit Card | G28: Citi Rewards
A29: 46137 | B29: Expense | C29: Misc | D29: Donation | E29: 125 | F29: Credit Card | G29: Citi Rewards
A30: 46138 | B30: Expense | C30: Subscription | D30: Youtube | E30: 17.98 | F30: Credit Card | G30: Citi Rewards
... A37: 46135 | B37: Expense | C37: Food | D37: Lunch with Team | E37: 18 | F37: Debit Card | G37: DBS
A38: 46136 | B38: Income | C38: Salary | D38: Nsfit | E38: 25.52 | G38: DBS
A39: 46139 | B39: Income | C39: Other Income | D39: CRWV stock profit | E39: 1482 | G39: DBS
A40: 46143 | B40: Expense | C40: Transport | D40: Parking | E40: 1.2 | G40: DBS
A41: 46138 | B41: Expense | C41: Grocery | D41: Fairprice | E41: 5.86 | F41: Credit Card | G41: Citi Rewards
A42: 46139 | B42: Expense | C42: Food | D42: Wokhey | E42: 7.9 | F42: Credit Card | G42: Citi Rewards
A43: 46139 | B43: Expense | C43: Food | E43: 0.17 | F43: Credit Card | G43: Citi Rewards
A44: 46140 | B44: Expense | C44: Food | D44: Citi Cafe | E44: 7.8 | F44: Credit Card | G44: Citi Rewards
A45: 46140 | B45: Expense | C45: Transport | D45: Bus | E45: 0.1 | F45: Credit Card | G45: Citi Rewards
A46: 46141 | B46: Expense | C46: Food | D46: Stuffd | E46: 11.5 | F46: Credit Card | G46: Citi Rewards
A47: 46142 | B47: Expense | C47: Food | D47: Andes | E47: 14.5 | F47: Credit Card | G47: Citi Rewards
A48: 46143 | B48: Expense | C48: Shopping | D48: Arenaclub Pokemon Slab | E48: 26.48 | F48: Credit Card | G48: Citi Rewards
A49: 46143 | B49: Expense | C49: Subscription | D49: Anytime Fitness | E49: 89 | F49: Credit Card | G49: Citi Cash+
A50: 46143 | B50: Expense | C50: Food | D50: DTF + Movie | E50: 75 | F50: Debit Card | G50: DBS
A51: 46144 | B51: Expense | C51: Shopping | D51: Pokemon Card | E51: 39.9 | F51: Debit Card | G51: DBS
A52: 46144 | B52: Expense | C52: Subscription | D52: Claude | E52: 30 | F52: Credit Card | G52: DBS
A53: 46143 | B53: Expense | C53: Food | D53: Drinks | E53: 4.8 | F53: Credit Card | G53: Citi Rewards
A54: 46143 | B54: Expense | C54: Food | D54: Breadtalk | E54: 6.1 | F54: Credit Card | G54: Citi Rewards
A55: 46144 | B55: Expense | C55: Food | D55: BK | E55: 6.5 | F55: Credit Card | G55: Citi Rewards
... A58: 46145 | B58: Expense | C58: Entertainment | D58: Movie | E58: 80 | F58: Debit Card | G58: DBS
A59: 46145 | B59: Expense | C59: Transport | D59: Car Wash | E59: 14 | F59: Cash
A60: 46146 | B60: Expense | C60: Food | D60: Tea | E60: 3.4 | F60: Debit Card | G60: DBS
A61: 46147 | B61: Expense | C61: Food | D61: Citi Cafe | E61: 8.5 | F61: Debit Card | G61: DBS
A62: 46148 | B62: Expense | C62: Bills | D62: Tax | E62: 240 | F62: Debit Card | G62: DBS
A63: 46148 | B63: Expense | C63: Transport | D63: Grab Taxi | E63: 13 | F63: Debit Card | G63: DBS
A64: 46149 | B64: Income | C64: Misc | D64: Arena Sales | E64: 16.38 | G64: DBS
A65: 46150 | B65: Income | C65: Other Income | D65: Nsfit | E65: 25.42 | G65: DBS
A66: 46150 | B66: Income | C66: Other Income | D66: Shopify | E66: 33.92 | G66: DBS
A67: 46151 | B67: Expense | C67: Subscription | D67: ChatGPT | E67: 28.59 | F67: Credit Card | G67: Yuu
A68: 46145 | B68: Expense | C68: Shopping | D68: Pokemon Card | E68: 19.9 | F68: Credit Card | G68: Citi Cash+
A69: 46145 | B69: Expense | C69: Shopping | D69: Pokemon Card | E69: 15.96 | F69: Credit Card | G69: Citi Cash+
A70: 46146 | B70: Expense | C70: Misc | D70: Donation | E70: 70 | F70: Credit Card | G70: Citi Cash+
A71: 46148 | B71: Expense | C71: Subscription | D71: NTUC membership | E71: 9 | F71: Credit Card | G71: Citi Cash+
A72: 46145 | B72: Expense | C72: Food | D72: Popcorn | E72: 20 | F72: Credit Card | G72: Citi Rewards
A73: 46146 | B73: Expense | C73: Grocery | D73: Fairprice | E73: 23.65 | F73: Credit Card | G73: Citi Rewards
A74: 46146 | B74: Expense | C74: Food | D74: Burger King | E74: 11.9 | F74: Credit Card | G74: Citi Rewards
A75: 46148 | B75: Expense | C75: Food | D75: Chicken Rice | E75: 7.1 | F75: Credit Card | G75: Citi Rewards
A76: 46149 | B76: Expense | C76: Food | D76: Chicken Rice | E76: 7.1 | F76: Credit Card | G76: Citi Rewards
A77: 46150 | B77: Expense | C77: Food | D77: Chicken Rice | E77: 7.1 | F77: Credit Card | G77: Citi Rewards
A78: 46151 | B78: Expense | C78: Shopping | D78: Nasal Strip | E78: 28.28 | F78: Credit Card | G78: Citi Rewards
A79: 46155 | B79: Income | C79: Misc | D79: AF Refund | E79: 89 | G79: Citi
A80: 46151 | B80: Expense | C80: Grocery | D80: Fairprice | E80: 14.12 | F80: Credit Card | G80: Citi Rewards
A81: 46151 | B81: Expense | C81: Food | D81: Bali Thai Mother's day | E81: 109.47 | F81: Credit Card | G81: Citi Rewards
A82: 46152 | B82: Expense | C82: Gift | D82: Mother's day flowers | E82: 55 | F82: Credit Card | G82: Citi Rewards
A83: 46152 | B83: Expense | C83: Food | D83: 4 Fingers | E83: 23 | F83: Credit Card | G83: Citi Rewards
A84: 46152 | B84: Expense | C84: Food | D84: Briyani | E84: 10.88 | F84: Credit Card | G84: Citi Rewards
A85: 46153 | B85: Expense | C85: Food | D85: Chicken Rice | E85: 5.1 | F85: Credit Card | G85: Citi Rewards
A86: 46154 | B86: Expense | C86: Food | D86: Chicken Rice | E86: 7.1 | F86: Credit Card | G86: Citi Rewards
A87: 46154 | B87: Expense | C87: Food | D87: Mcd | E87: 19.35 | F87: Credit Card | G87: Citi Rewards
A88: 46155 | B88: Expense | C88: Food | D88: Chicken Rice | E88: 7.1 | F88: Credit Card | G88: Citi Rewards
A89: 46156 | B89: Expense | C89: Food | D89: Wokhey | E89: 9.4 | F89: Credit Card | G89: Citi Rewards
A90: 46156 | B90: Expense | C90: Grocery | D90: Fairprice | E90: 16.91 | F90: Credit Card | G90: Citi Rewards
A91: 46154 | B91: Expense | C91: Food | D91: Tea | E91: 5.3 | F91: Debit Card | G91: DBS
... A108: 46161 | B108: Expense | C108: Shopping | D108: Keychain | E108: 8.32 | F108: Credit Card | G108: Citi Rewards
A109: 46160 | B109: Income | C109: Salary | D109: Salary | E109: 6529.67 | F109: GIRO
A110: 46158 | B110: Expense | C110: Shopping | D110: KL Shopping | E110: 12.7 | F110: Credit Card | G110: Citi Cash+
A111: 46158 | B111: Expense | C111: Shopping | D111: KL Shopping | E111: 3.95 | F111: Credit Card | G111: Citi Cash+
A112: 46158 | B112: Expense | C112: Food | D112: KL Coffee | E112: 6.62 | F112: Credit Card | G112: Citi Cash+
A113: 46158 | B113: Expense | C113: Shopping | D113: KL Shopping | E113: 24.93 | F113: Credit Card | G113: Citi Cash+
A114: 46158 | B114: Expense | C114: Shopping | D114: KL Shopping | E114: 39.23 | F114: Credit Card | G114: Citi Cash+
A115: 46158 | B115: Expense | C115: Food | D115: KL Sushiro | E115: 74.81 | F115: Credit Card | G115: Citi Cash+
A116: 46158 | B116: Expense | C116: Travel | D116: KL Grand Hyatt Deposit | E116: 199.45 | F116: Credit Card | G116: Citi Cash+
A117: 46158 | B117: Expense | C117: Travel | D117: KL Monorail | E117: 1.8 | F117: Credit Card | G117: Citi Cash+
A118: 46159 | B118: Expense | C118: Subscription | D118: Prime | E118: 4.99 | F118: Credit Card | G118: Citi Cash+
A119: 46159 | B119: Expense | C119: Food | D119: KL Sushi | E119: 4.26 | F119: Credit Card | G119: Citi Cash+
A120: 46159 | B120: Expense | C120: Shopping | D120: KL Uniqlo | E120: 49.93 | F120: Credit Card | G120: Citi Cash+
A121: 46159 | B121: Expense | C121: Food | D121: KL Coffee | E121: 4.36 | F121: Credit Card | G121: Citi Cash+
... A131: 46169 | B131: Expense | C131: Food | D131: Coffee | E131: 5.9 | F131: Debit Card | G131: DBS
A132: 46171 | B132: Income | C132: Other Income | D132: NSfit | E132: 24.6 | G132: DBS
A133: 46172 | B133: Expense | C133: Transport | D133: Grab Taxi | E133: 35 | F133: Debit Card | G133: DBS
A134: 46170 | B134: Expense | C134: Education | D134: Tribe Java | E134: 8.88 | F134: Debit Card | G134: DBS
...

Sheet Dashboard
B2: Personal Finance Dashboard
B3: Auto-syncs from the Transactions tab — all figures in SGD
B5: Total Income (This Month) | D5: Total Expense (This Month) | F5: Net Cashflow (This Month)
B6: =SUMIFS(Transactions!E:E,Transactions!B:B,"Income",Transactions!A:A,">="&DATE(YEAR(TODAY()),MONTH(TODAY()),1),Transactions!A:A,"<="&EOMONTH(TODAY(),0)) -> 6776.5 | D6: =SUMIFS(Transactions!E:E,Transactions!B:B,"Expense",Transactions!A:A,">="&DATE(YEAR(TODAY()),MONTH(TODAY()),1),Transactions!A:A,"<="&EOMONTH(TODAY(),0)) -> 3776.96 | F6: =B6-D6 -> 2999.54
B8: Biggest Expense Category | D8: Avg Daily Spending (This Month) | F8: Transactions Logged (This Month)
B9: {=IFERROR(INDEX($J$22:$J$32,MATCH(MAX($K$22:$K$32),$K$22:$K$32,0)),"—")} -> Family | D9: =IFERROR(D6/DAY(EOMONTH(TODAY(),0)),0) -> 121.83742 | F9: =COUNTIFS(Transactions!A:A,">="&DATE(YEAR(TODAY()),MONTH(TODAY()),1),Transactions!A:A,"<="&EOMONTH(TODAY(),0)) -> 104
J11: Monthly Trend (Income vs Expense)
J12: Month | K12: Income | L12: Expense
J13: Feb 2026 | K13: =SUMIFS(Transactions!E:E,Transactions!B:B,"Income",Transactions!A:A,">="&DATE(2026,2,1),Transactions!A:A,"<"&DATE(2026,3,1)) -> 0 | L13: =SUMIFS(Transactions!E:E,Transactions!B:B,"Expense",Transactions!A:A,">="&DATE(2026,2,1),Transactions!A:A,"<"&DATE(2026,3,1)) -> 0
J14: Mar 2026 | K14: =SUMIFS(Transactions!E:E,Transactions!B:B,"Income",Transactions!A:A,">="&DATE(2026,3,1),Transactions!A:A,"<"&DATE(2026,4,1)) -> 0 | L14: =SUMIFS(Transactions!E:E,Transactions!B:B,"Expense",Transactions!A:A,">="&DATE(2026,3,1),Transactions!A:A,"<"&DATE(2026,4,1)) -> 0
J15: Apr 2026 | K15: =SUMIFS(Transactions!E:E,Transactions!B:B,"Income",Transactions!A:A,">="&DATE(2026,4,1),Transactions!A:A,"<"&DATE(2026,5,1)) -> 8681.09 | L15: =SUMIFS(Transactions!E:E,Transactions!B:B,"Expense",Transactions!A:A,">="&DATE(2026,4,1),Transactions!A:A,"<"&DATE(2026,5,1)) -> 590.359
J16: May 2026 | K16: =SUMIFS(Transactions!E:E,Transactions!B:B,"Income",Transactions!A:A,">="&DATE(2026,5,1),Transactions!A:A,"<"&DATE(2026,6,1)) -> 6776.5 | L16: =SUMIFS(Transactions!E:E,Transactions!B:B,"Expense",Transactions!A:A,">="&DATE(2026,5,1),Transactions!A:A,"<"&DATE(2026,6,1)) -> 3776.96
J17: Jun 2026 | K17: =SUMIFS(Transactions!E:E,Transactions!B:B,"Income",Transactions!A:A,">="&DATE(2026,6,1),Transactions!A:A,"<"&DATE(2026,7,1)) -> 0 | L17: =SUMIFS(Transactions!E:E,Transactions!B:B,"Expense",Transactions!A:A,">="&DATE(2026,6,1),Transactions!A:A,"<"&DATE(2026,7,1)) -> 0
J18: Jul 2026 | K18: =SUMIFS(Transactions!E:E,Transactions!B:B,"Income",Transactions!A:A,">="&DATE(2026,7,1),Transactions!A:A,"<"&DATE(2026,8,1)) -> 0 | L18: =SUMIFS(Transactions!E:E,Transactions!B:B,"Expense",Transactions!A:A,">="&DATE(2026,7,1),Transactions!A:A,"<"&DATE(2026,8,1)) -> 0
J20: Expense by Category (All-Time)
J21: Category | K21: Amount
J22: Food | K22: =SUMIFS(Transactions!E:E,Transactions!B:B,"Expense",Transactions!C:C,"Food") -> 847.14
J23: Transport | K23: =SUMIFS(Transactions!E:E,Transactions!B:B,"Expense",Transactions!C:C,"Transport") -> 110.18
J24: Bills | K24: =SUMIFS(Transactions!E:E,Transactions!B:B,"Expense",Transactions!C:C,"Bills") -> 240
J25: Shopping | K25: =SUMIFS(Transactions!E:E,Transactions!B:B,"Expense",Transactions!C:C,"Shopping") -> 486.98
J26: Subscription | K26: =SUMIFS(Transactions!E:E,Transactions!B:B,"Expense",Transactions!C:C,"Subscription") -> 437.369
J27: Entertainment | K27: =SUMIFS(Transactions!E:E,Transactions!B:B,"Expense",Transactions!C:C,"Entertainment") -> 180
J28: Health | K28: =SUMIFS(Transactions!E:E,Transactions!B:B,"Expense",Transactions!C:C,"Health") -> 0
J29: Family | K29: =SUMIFS(Transactions!E:E,Transactions!B:B,"Expense",Transactions!C:C,"Family") -> 1000
J30: Travel | K30: =SUMIFS(Transactions!E:E,Transactions!B:B,"Expense",Transactions!C:C,"Travel") -> 563.95
J31: Education | K31: =SUMIFS(Transactions!E:E,Transactions!B:B,"Expense",Transactions!C:C,"Education") -> 8.88
J32: Misc | K32: =SUMIFS(Transactions!E:E,Transactions!B:B,"Expense",Transactions!C:C,"Misc") -> 199
J34: Weekly Spending Trend
J35: Week Start | K35: Spending
J36: 46048 | K36: =SUMIFS(Transactions!E:E,Transactions!B:B,"Expense",Transactions!A:A,">="&DATE(2026,1,26),Transactions!A:A,"<"&DATE(2026,2,2)) -> 0
J37: 46055 | K37: =SUMIFS(Transactions!E:E,Transactions!B:B,"Expense",Transactions!A:A,">="&DATE(2026,2,2),Transactions!A:A,"<"&DATE(2026,2,9)) -> 0
J38: 46062 | K38: =SUMIFS(Transactions!E:E,Transactions!B:B,"Expense",Transactions!A:A,">="&DATE(2026,2,9),Transactions!A:A,"<"&DATE(2026,2,16)) -> 0
J39: 46069 | K39: =SUMIFS(Transactions!E:E,Transactions!B:B,"Expense",Transactions!A:A,">="&DATE(2026,2,16),Transactions!A:A,"<"&DATE(2026,2,23)) -> 0
J40: 46076 | K40: =SUMIFS(Transactions!E:E,Transactions!B:B,"Expense",Transactions!A:A,">="&DATE(2026,2,23),Transactions!A:A,"<"&DATE(2026,3,2)) -> 0
J41: 46083 | K41: =SUMIFS(Transactions!E:E,Transactions!B:B,"Expense",Transactions!A:A,">="&DATE(2026,3,2),Transactions!A:A,"<"&DATE(2026,3,9)) -> 0
J42: 46090 | K42: =SUMIFS(Transactions!E:E,Transactions!B:B,"Expense",Transactions!A:A,">="&DATE(2026,3,9),Transactions!A:A,"<"&DATE(2026,3,16)) -> 0
J43: 46097 | K43: =SUMIFS(Transactions!E:E,Transactions!B:B,"Expense",Transactions!A:A,">="&DATE(2026,3,16),Transactions!A:A,"<"&DATE(2026,3,23)) -> 0
J44: 46104 | K44: =SUMIFS(Transactions!E:E,Transactions!B:B,"Expense",Transactions!A:A,">="&DATE(2026,3,23),Transactions!A:A,"<"&DATE(2026,3,30)) -> 0
J45: 46111 | K45: =SUMIFS(Transactions!E:E,Transactions!B:B,"Expense",Transactions!A:A,">="&DATE(2026,3,30),Transactions!A:A,"<"&DATE(2026,4,6)) -> 0
J46: 46118 | K46: =SUMIFS(Transactions!E:E,Transactions!B:B,"Expense",Transactions!A:A,">="&DATE(2026,4,6),Transactions!A:A,"<"&DATE(2026,4,13)) -> 0
J47: 46125 | K47: =SUMIFS(Transactions!E:E,Transactions!B:B,"Expense",Transactions!A:A,">="&DATE(2026,4,13),Transactions!A:A,"<"&DATE(2026,4,20)) -> 168.099
J50: Top 5 Expense Categories
J51: Rank | K51: Category | L51: Amount
J52: 1 | K52: {=IFERROR(INDEX($J$22:$J$32,MATCH(LARGE($K$22:$K$32,1),$K$22:$K$32,0)),"")} -> Family | L52: =IFERROR(LARGE($K$22:$K$32,1),0) -> 1000
J53: 2 | K53: {=IFERROR(INDEX($J$22:$J$32,MATCH(LARGE($K$22:$K$32,2),$K$22:$K$32,0)),"")} -> Food | L53: =IFERROR(LARGE($K$22:$K$32,2),0) -> 847.14
J54: 3 | K54: {=IFERROR(INDEX($J$22:$J$32,MATCH(LARGE($K$22:$K$32,3),$K$22:$K$32,0)),"")} -> Travel | L54: =IFERROR(LARGE($K$22:$K$32,3),0) -> 563.95
J55: 4 | K55: {=IFERROR(INDEX($J$22:$J$32,MATCH(LARGE($K$22:$K$32,4),$K$22:$K$32,0)),"")} -> Shopping | L55: =IFERROR(LARGE($K$22:$K$32,4),0) -> 486.98
J56: 5 | K56: {=IFERROR(INDEX($J$22:$J$32,MATCH(LARGE($K$22:$K$32,5),$K$22:$K$32,0)),"")} -> Subscription | L56: =IFERROR(LARGE($K$22:$K$32,5),0) -> 437.369

Sheet Report
B2: Financial Report | Z2: =IFERROR(IF(Transactions!B2="Expense",Transactions!E2+ROW()/10000000,""),"") | AA2: =IFERROR(IF(Transactions!B2="Expense",Transactions!A2,""),"") | AB2: =IFERROR(IF(Transactions!B2="Expense",Transactions!C2,""),"") | AC2: =IFERROR(IF(Transactions!B2="Expense",Transactions!D2,""),"") | AD2: =IFERROR(IF(Transactions!B2="Expense",Transactions!E2,""),"")
B3: Auto-generated summaries from Transactions | Z3: =IFERROR(IF(Transactions!B3="Expense",Transactions!E3+ROW()/10000000,""),"") -> 4.9990003 | AA3: =IFERROR(IF(Transactions!B3="Expense",Transactions!A3,""),"") -> 46127 | AB3: =IFERROR(IF(Transactions!B3="Expense",Transactions!C3,""),"") -> Subscription | AC3: =IFERROR(IF(Transactions!B3="Expense",Transactions!D3,""),"") -> Prime | AD3: =IFERROR(IF(Transactions!B3="Expense",Transactions!E3,""),"") -> 4.999
Z4: =IFERROR(IF(Transactions!B4="Expense",Transactions!E4+ROW()/10000000,""),"") -> 6.5800004 | AA4: =IFERROR(IF(Transactions!B4="Expense",Transactions!A4,""),"") -> 46130 | AB4: =IFERROR(IF(Transactions!B4="Expense",Transactions!C4,""),"") -> Shopping | AC4: =IFERROR(IF(Transactions!B4="Expense",Transactions!D4,""),"") -> Shoppee | AD4: =IFERROR(IF(Transactions!B4="Expense",Transactions!E4,""),"") -> 6.58
B5: 1. Monthly Summary | Z5: =IFERROR(IF(Transactions!B5="Expense",Transactions!E5+ROW()/10000000,""),"") -> 5.4600005 | AA5: =IFERROR(IF(Transactions!B5="Expense",Transactions!A5,""),"") -> 46131 | AB5: =IFERROR(IF(Transactions!B5="Expense",Transactions!C5,""),"") -> Shopping | AC5: =IFERROR(IF(Transactions!B5="Expense",Transactions!D5,""),"") -> Shoppee | AD5: =IFERROR(IF(Transactions!B5="Expense",Transactions!E5,""),"") -> 5.46
B6: Month | C6: Income | D6: Expense | E6: Net Savings | F6: Savings Rate | Z6: =IFERROR(IF(Transactions!B6="Expense",Transactions!E6+ROW()/10000000,""),"") -> 6.5400006 | AA6: =IFERROR(IF(Transactions!B6="Expense",Transactions!A6,""),"") -> 46127 | AB6: =IFERROR(IF(Transactions!B6="Expense",Transactions!C6,""),"") -> Shopping | AC6: =IFERROR(IF(Transactions!B6="Expense",Transactions!D6,""),"") -> Tiktok | AD6: =IFERROR(IF(Transactions!B6="Expense",Transactions!E6,""),"") -> 6.54
B7: Apr 2026 | C7: =SUMIFS(Transactions!E:E,Transactions!B:B,"Income",Transactions!A:A,">="&DATE(2026,4,1),Transactions!A:A,"<"&DATE(2026,5,1)) -> 8681.09 | D7: =SUMIFS(Transactions!E:E,Transactions!B:B,"Expense",Transactions!A:A,">="&DATE(2026,4,1),Transactions!A:A,"<"&DATE(2026,5,1)) -> 590.359 | E7: =C7-D7 -> 8090.731 | F7: =IFERROR((C7-D7)/C7,0) -> 0.93199483 | Z7: =IFERROR(IF(Transactions!B9="Expense",Transactions!E9+ROW()/10000000,""),"") -> 8.1000007 | AA7: =IFERROR(IF(Transactions!B9="Expense",Transactions!A9,""),"") -> 46129 | AB7: =IFERROR(IF(Transactions!B9="Expense",Transactions!C9,""),"") -> Food | AC7: =IFERROR(IF(Transactions!B9="Expense",Transactions!D9,""),"") -> Chicken Rice | AD7: =IFERROR(IF(Transactions!B9="Expense",Transactions!E9,""),"") -> 8.1
B8: May 2026 | C8: =SUMIFS(Transactions!E:E,Transactions!B:B,"Income",Transactions!A:A,">="&DATE(2026,5,1),Transactions!A:A,"<"&DATE(2026,6,1)) -> 6776.5 | D8: =SUMIFS(Transactions!E:E,Transactions!B:B,"Expense",Transactions!A:A,">="&DATE(2026,5,1),Transactions!A:A,"<"&DATE(2026,6,1)) -> 3776.96 | E8: =C8-D8 -> 2999.54 | F8: =IFERROR((C8-D8)/C8,0) -> 0.44263853 | Z8: =IFERROR(IF(Transactions!B10="Expense",Transactions!E10+ROW()/10000000,""),"") -> 16.500001 | AA8: =IFERROR(IF(Transactions!B10="Expense",Transactions!A10,""),"") -> 46130 | AB8: =IFERROR(IF(Transactions!B10="Expense",Transactions!C10,""),"") -> Shopping | AC8: =IFERROR(IF(Transactions!B10="Expense",Transactions!D10,""),"") -> Amazon Cookie | AD8: =IFERROR(IF(Transactions!B10="Expense",Transactions!E10,""),"") -> 16.5
B9: Jun 2026 | C9: =SUMIFS(Transactions!E:E,Transactions!B:B,"Income",Transactions!A:A,">="&DATE(2026,6,1),Transactions!A:A,"<"&DATE(2026,7,1)) -> 0 | D9: =SUMIFS(Transactions!E:E,Transactions!B:B,"Expense",Transactions!A:A,">="&DATE(2026,6,1),Transactions!A:A,"<"&DATE(2026,7,1)) -> 0 | E9: =C9-D9 -> 0 | F9: =IFERROR((C9-D9)/C9,0) -> 0 | Z9: =IFERROR(IF(Transactions!B11="Expense",Transactions!E11+ROW()/10000000,""),"") -> 13.980001 | AA9: =IFERROR(IF(Transactions!B11="Expense",Transactions!A11,""),"") -> 46130 | AB9: =IFERROR(IF(Transactions!B11="Expense",Transactions!C11,""),"") -> Subscription | AC9: =IFERROR(IF(Transactions!B11="Expense",Transactions!D11,""),"") -> iCloud | AD9: =IFERROR(IF(Transactions!B11="Expense",Transactions!E11,""),"") -> 13.98
B10: Jul 2026 | C10: =SUMIFS(Transactions!E:E,Transactions!B:B,"Income",Transactions!A:A,">="&DATE(2026,7,1),Transactions!A:A,"<"&DATE(2026,8,1)) -> 0 | D10: =SUMIFS(Transactions!E:E,Transactions!B:B,"Expense",Transactions!A:A,">="&DATE(2026,7,1),Transactions!A:A,"<"&DATE(2026,8,1)) -> 0 | E10: =C10-D10 -> 0 | F10: =IFERROR((C10-D10)/C10,0) -> 0 | Z10: =IFERROR(IF(Transactions!B12="Expense",Transactions!E12+ROW()/10000000,""),"") -> 25.880001 | AA10: =IFERROR(IF(Transactions!B12="Expense",Transactions!A12,""),"") -> 46130 | AB10: =IFERROR(IF(Transactions!B12="Expense",Transactions!C12,""),"") -> Grocery | AC10: =IFERROR(IF(Transactions!B12="Expense",Transactions!D12,""),"") -> Fairprice | AD10: =IFERROR(IF(Transactions!B12="Expense",Transactions!E12,""),"") -> 25.88
B11: Total | C11: =SUM(C7:C10) -> 15457.59 | D11: =SUM(D7:D10) -> 4367.319 | E11: =SUM(E7:E10) -> 11090.271 | F11: =IFERROR(E11/C11,0) -> 0.71746443 | Z11: =IFERROR(IF(Transactions!B13="Expense",Transactions!E13+ROW()/10000000,""),"") -> 18.000001 | AA11: =IFERROR(IF(Transactions!B13="Expense",Transactions!A13,""),"") -> 46131 | AB11: =IFERROR(IF(Transactions!B13="Expense",Transactions!C13,""),"") -> Entertainment | AC11: =IFERROR(IF(Transactions!B13="Expense",Transactions!D13,""),"") -> Pokemon Card | AD11: =IFERROR(IF(Transactions!B13="Expense",Transactions!E13,""),"") -> 18
Z12: =IFERROR(IF(Transactions!B14="Expense",Transactions!E14+ROW()/10000000,""),"") -> 17.460001 | AA12: =IFERROR(IF(Transactions!B14="Expense",Transactions!A14,""),"") -> 46129 | AB12: =IFERROR(IF(Transactions!B14="Expense",Transactions!C14,""),"") -> Subscription | AC12: =IFERROR(IF(Transactions!B14="Expense",Transactions!D14,""),"") -> Spotify | AD12: =IFERROR(IF(Transactions!B14="Expense",Transactions!E14,""),"") -> 17.46
Z13: =IFERROR(IF(Transactions!B15="Expense",Transactions!E15+ROW()/10000000,""),"") -> 11.800001 | AA13: =IFERROR(IF(Transactions!B15="Expense",Transactions!A15,""),"") -> 46127 | AB13: =IFERROR(IF(Transactions!B15="Expense",Transactions!C15,""),"") -> Food | AC13: =IFERROR(IF(Transactions!B15="Expense",Transactions!D15,""),"") -> Wokhey | AD13: =IFERROR(IF(Transactions!B15="Expense",Transactions!E15,""),"") -> 11.8
B14: 2. Category Spending Breakdown (All-Time) | Z14: =IFERROR(IF(Transactions!B16="Expense",Transactions!E16+ROW()/10000000,""),"") -> 13.700001 | AA14: =IFERROR(IF(Transactions!B16="Expense",Transactions!A16,""),"") -> 46131 | AB14: =IFERROR(IF(Transactions!B16="Expense",Transactions!C16,""),"") -> Food | AC14: =IFERROR(IF(Transactions!B16="Expense",Transactions!D16,""),"") -> Popeye | AD14: =IFERROR(IF(Transactions!B16="Expense",Transactions!E16,""),"") -> 13.7
B15: Category | C15: Total Spent | D15: % of Expense | E15: # of Txns | F15: Avg per Txn | Z15: =IFERROR(IF(Transactions!B17="Expense",Transactions!E17+ROW()/10000000,""),"") | AA15: =IFERROR(IF(Transactions!B17="Expense",Transactions!A17,""),"") | AB15: =IFERROR(IF(Transactions!B17="Expense",Transactions!C17,""),"") | AC15: =IFERROR(IF(Transactions!B17="Expense",Transactions!D17,""),"") | AD15: =IFERROR(IF(Transactions!B17="Expense",Transactions!E17,""),"")
B16: Food | C16: =SUMIFS(Transactions!E:E,Transactions!B:B,"Expense",Transactions!C:C,"Food") -> 847.14 | D16: =IFERROR(C16/SUMIFS(Transactions!E:E,Transactions!B:B,"Expense"),0) -> 0.19397255 | E16: =COUNTIFS(Transactions!B:B,"Expense",Transactions!C:C,"Food") -> 57 | F16: =IFERROR(C16/E16,0) -> 14.862105 | Z16: =IFERROR(IF(Transactions!B18="Expense",Transactions!E18+ROW()/10000000,""),"") | AA16: =IFERROR(IF(Transactions!B18="Expense",Transactions!A18,""),"") | AB16: =IFERROR(IF(Transactions!B18="Expense",Transactions!C18,""),"") | AC16: =IFERROR(IF(Transactions!B18="Expense",Transactions!D18,""),"") | AD16: =IFERROR(IF(Transactions!B18="Expense",Transactions!E18,""),"")
B17: Transport | C17: =SUMIFS(Transactions!E:E,Transactions!B:B,"Expense",Transactions!C:C,"Transport") -> 110.18 | D17: =IFERROR(C17/SUMIFS(Transactions!E:E,Transactions!B:B,"Expense"),0) -> 0.025228292 | E17: =COUNTIFS(Transactions!B:B,"Expense",Transactions!C:C,"Transport") -> 10 | F17: =IFERROR(C17/E17,0) -> 11.018 | Z17: =IFERROR(IF(Transactions!B19="Expense",Transactions!E19+ROW()/10000000,""),"") -> 13.000002 | AA17: =IFERROR(IF(Transactions!B19="Expense",Transactions!A19,""),"") -> 46131 | AB17: =IFERROR(IF(Transactions!B19="Expense",Transactions!C19,""),"") -> Food | AC17: =IFERROR(IF(Transactions!B19="Expense",Transactions!D19,""),"") -> Subway | AD17: =IFERROR(IF(Transactions!B19="Expense",Transactions!E19,""),"") -> 13
B18: Bills | C18: =SUMIFS(Transactions!E:E,Transactions!B:B,"Expense",Transactions!C:C,"Bills") -> 240 | D18: =IFERROR(C18/SUMIFS(Transactions!E:E,Transactions!B:B,"Expense"),0) -> 0.054953623 | E18: =COUNTIFS(Transactions!B:B,"Expense",Transactions!C:C,"Bills") -> 1 | F18: =IFERROR(C18/E18,0) -> 240 | Z18: =IFERROR(IF(Transactions!B20="Expense",Transactions!E20+ROW()/10000000,""),"") -> 7.1000018 | AA18: =IFERROR(IF(Transactions!B20="Expense",Transactions!A20,""),"") -> 46132 | AB18: =IFERROR(IF(Transactions!B20="Expense",Transactions!C20,""),"") -> Food | AC18: =IFERROR(IF(Transactions!B20="Expense",Transactions!D20,""),"") -> Chicken Rice | AD18: =IFERROR(IF(Transactions!B20="Expense",Transactions!E20,""),"") -> 7.1
B19: Shopping | C19: =SUMIFS(Transactions!E:E,Transactions!B:B,"Expense",Transactions!C:C,"Shopping") -> 486.98 | D19: =IFERROR(C19/SUMIFS(Transactions!E:E,Transactions!B:B,"Expense"),0) -> 0.11150548 | E19: =COUNTIFS(Transactions!B:B,"Expense",Transactions!C:C,"Shopping") -> 20 | F19: =IFERROR(C19/E19,0) -> 24.349 | Z19: =IFERROR(IF(Transactions!B21="Expense",Transactions!E21+ROW()/10000000,""),"") -> 0.2000019 | AA19: =IFERROR(IF(Transactions!B21="Expense",Transactions!A21,""),"") -> 46132 | AB19: =IFERROR(IF(Transactions!B21="Expense",Transactions!C21,""),"") -> Transport | AC19: =IFERROR(IF(Transactions!B21="Expense",Transactions!D21,""),"") -> Bus | AD19: =IFERROR(IF(Transactions!B21="Expense",Transactions!E21,""),"") -> 0.2
B20: Subscription | C20: =SUMIFS(Transactions!E:E,Transactions!B:B,"Expense",Transactions!C:C,"Subscription") -> 437.369 | D20: =IFERROR(C20/SUMIFS(Transactions!E:E,Transactions!B:B,"Expense"),0) -> 0.10014588 | E20: =COUNTIFS(Transactions!B:B,"Expense",Transactions!C:C,"Subscription") -> 18 | F20: =IFERROR(C20/E20,0) -> 24.298278 | Z20: =IFERROR(IF(Transactions!B22="Expense",Transactions!E22+ROW()/10000000,""),"") -> 14.440002 | AA20: =IFERROR(IF(Transactions!B22="Expense",Transactions!A22,""),"") -> 46132 | AB20: =IFERROR(IF(Transactions!B22="Expense",Transactions!C22,""),"") -> Grocery | AC20: =IFERROR(IF(Transactions!B22="Expense",Transactions!D22,""),"") -> Fairprice | AD20: =IFERROR(IF(Transactions!B22="Expense",Transactions!E22,""),"") -> 14.44
B21: Entertainment | C21: =SUMIFS(Transactions!E:E,Transactions!B:B,"Expense",Transactions!C:C,"Entertainment") -> 180 | D21: =IFERROR(C21/SUMIFS(Transactions!E:E,Transactions!B:B,"Expense"),0) -> 0.041215217 | E21: =COUNTIFS(Transactions!B:B,"Expense",Transactions!C:C,"Entertainment") -> 4 | F21: =IFERROR(C21/E21,0) -> 45 | Z21: =IFERROR(IF(Transactions!B23="Expense",Transactions!E23+ROW()/10000000,""),"") -> 18.270002 | AA21: =IFERROR(IF(Transactions!B23="Expense",Transactions!A23,""),"") -> 46132 | AB21: =IFERROR(IF(Transactions!B23="Expense",Transactions!C23,""),"") -> Grocery | AC21: =IFERROR(IF(Transactions!B23="Expense",Transactions!D23,""),"") -> Fairprice | AD21: =IFERROR(IF(Transactions!B23="Expense",Transactions!E23,""),"") -> 18.27
B22: Health | C22: =SUMIFS(Transactions!E:E,Transactions!B:B,"Expense",Transactions!C:C,"Health") -> 0 | D22: =IFERROR(C22/SUMIFS(Transactions!E:E,Transactions!B:B,"Expense"),0) -> 0 | E22: =COUNTIFS(Transactions!B:B,"Expense",Transactions!C:C,"Health") -> 0 | F22: =IFERROR(C22/E22,0) -> 0 | Z22: =IFERROR(IF(Transactions!B24="Expense",Transactions!E24+ROW()/10000000,""),"") -> 5.4000022 | AA22: =IFERROR(IF(Transactions!B24="Expense",Transactions!A24,""),"") -> 46134 | AB22: =IFERROR(IF(Transactions!B24="Expense",Transactions!C24,""),"") -> Food | AC22: =IFERROR(IF(Transactions!B24="Expense",Transactions!D24,""),"") -> Chicken Rice | AD22: =IFERROR(IF(Transactions!B24="Expense",Transactions!E24,""),"") -> 5.4
B23: Family | C23: =SUMIFS(Transactions!E:E,Transactions!B:B,"Expense",Transactions!C:C,"Family") -> 1000 | D23: =IFERROR(C23/SUMIFS(Transactions!E:E,Transactions!B:B,"Expense"),0) -> 0.22897343 | E23: =COUNTIFS(Transactions!B:B,"Expense",Transactions!C:C,"Family") -> 1 | F23: =IFERROR(C23/E23,0) -> 1000 | Z23: =IFERROR(IF(Transactions!B25="Expense",Transactions!E25+ROW()/10000000,""),"") -> 5.1000023 | AA23: =IFERROR(IF(Transactions!B25="Expense",Transactions!A25,""),"") -> 46134 | AB23: =IFERROR(IF(Transactions!B25="Expense",Transactions!C25,""),"") -> Food | AC23: =IFERROR(IF(Transactions!B25="Expense",Transactions!D25,""),"") -> Siew Mai | AD23: =IFERROR(IF(Transactions!B25="Expense",Transactions!E25,""),"") -> 5.1
B24: Travel | C24: =SUMIFS(Transactions!E:E,Transactions!B:B,"Expense",Transactions!C:C,"Travel") -> 563.95 | D24: =IFERROR(C24/SUMIFS(Transactions!E:E,Transactions!B:B,"Expense"),0) -> 0.12912956 | E24: =COUNTIFS(Transactions!B:B,"Expense",Transactions!C:C,"Travel") -> 5 | F24: =IFERROR(C24/E24,0) -> 112.79 | Z24: =IFERROR(IF(Transactions!B26="Expense",Transactions!E26+ROW()/10000000,""),"") -> 3.1000024 | AA24: =IFERROR(IF(Transactions!B26="Expense",Transactions!A26,""),"") -> 46134 | AB24: =IFERROR(IF(Transactions!B26="Expense",Transactions!C26,""),"") -> Grocery | AC24: =IFERROR(IF(Transactions!B26="Expense",Transactions!D26,""),"") -> Fairprice | AD24: =IFERROR(IF(Transactions!B26="Expense",Transactions!E26,""),"") -> 3.1
B25: Education | C25: =SUMIFS(Transactions!E:E,Transactions!B:B,"Expense",Transactions!C:C,"Education") -> 8.88 | D25: =IFERROR(C25/SUMIFS(Transactions!E:E,Transactions!B:B,"Expense"),0) -> 0.002033284 | E25: =COUNTIFS(Transactions!B:B,"Expense",Transactions!C:C,"Education") -> 1 | F25: =IFERROR(C25/E25,0) -> 8.88 | Z25: =IFERROR(IF(Transactions!B27="Expense",Transactions!E27+ROW()/10000000,""),"") -> 0.2000025 | AA25: =IFERROR(IF(Transactions!B27="Expense",Transactions!A27,""),"") -> 46135 | AB25: =IFERROR(IF(Transactions!B27="Expense",Transactions!C27,""),"") -> Transport | AC25: =IFERROR(IF(Transactions!B27="Expense",Transactions!D27,""),"") -> Bus | AD25: =IFERROR(IF(Transactions!B27="Expense",Transactions!E27,""),"") -> 0.2
B26: Misc | C26: =SUMIFS(Transactions!E:E,Transactions!B:B,"Expense",Transactions!C:C,"Misc") -> 199 | D26: =IFERROR(C26/SUMIFS(Transactions!E:E,Transactions!B:B,"Expense"),0) -> 0.045565712 | E26: =COUNTIFS(Transactions!B:B,"Expense",Transactions!C:C,"Misc") -> 4 | F26: =IFERROR(C26/E26,0) -> 49.75 | Z26: =IFERROR(IF(Transactions!B28="Expense",Transactions!E28+ROW()/10000000,""),"") -> 15.100003 | AA26: =IFERROR(IF(Transactions!B28="Expense",Transactions!A28,""),"") -> 46136 | AB26: =IFERROR(IF(Transactions!B28="Expense",Transactions!C28,""),"") -> Food | AC26: =IFERROR(IF(Transactions!B28="Expense",Transactions!D28,""),"") -> Stuffd | AD26: =IFERROR(IF(Transactions!B28="Expense",Transactions!E28,""),"") -> 15.1
B27: Grocery | C27: =SUMIFS(Transactions!E:E,Transactions!B:B,"Expense",Transactions!C:C,"Grocery") -> 238.82 | D27: =IFERROR(C27/SUMIFS(Transactions!E:E,Transactions!B:B,"Expense"),0) -> 0.054683434 | E27: =COUNTIFS(Transactions!B:B,"Expense",Transactions!C:C,"Grocery") -> 14 | F27: =IFERROR(C27/E27,0) -> 17.058571 | Z27: =IFERROR(IF(Transactions!B29="Expense",Transactions!E29+ROW()/10000000,""),"") -> 125 | AA27: =IFERROR(IF(Transactions!B29="Expense",Transactions!A29,""),"") -> 46137 | AB27: =IFERROR(IF(Transactions!B29="Expense",Transactions!C29,""),"") -> Misc | AC27: =IFERROR(IF(Transactions!B29="Expense",Transactions!D29,""),"") -> Donation | AD27: =IFERROR(IF(Transactions!B29="Expense",Transactions!E29,""),"") -> 125
B28: 3. Top 10 Largest Expenses | Z28: =IFERROR(IF(Transactions!B30="Expense",Transactions!E30+ROW()/10000000,""),"") -> 17.980003 | AA28: =IFERROR(IF(Transactions!B30="Expense",Transactions!A30,""),"") -> 46138 | AB28: =IFERROR(IF(Transactions!B30="Expense",Transactions!C30,""),"") -> Subscription | AC28: =IFERROR(IF(Transactions!B30="Expense",Transactions!D30,""),"") -> Youtube | AD28: =IFERROR(IF(Transactions!B30="Expense",Transactions!E30,""),"") -> 17.98
B29: Rank | C29: Date | D29: Category | E29: Description | F29: Amount | Z29: =IFERROR(IF(Transactions!B31="Expense",Transactions!E31+ROW()/10000000,""),"") -> 82.620003 | AA29: =IFERROR(IF(Transactions!B31="Expense",Transactions!A31,""),"") -> 46138 | AB29: =IFERROR(IF(Transactions!B31="Expense",Transactions!C31,""),"") -> Subscription | AC29: =IFERROR(IF(Transactions!B31="Expense",Transactions!D31,""),"") -> AVG Antivirus | AD29: =IFERROR(IF(Transactions!B31="Expense",Transactions!E31,""),"") -> 82.62
B30: 1 | C30: {=IFERROR(INDEX($AA$2:$AA$499,MATCH(LARGE($Z$2:$Z$499,1),$Z$2:$Z$499,0)),"")} -> 46170 | D30: {=IFERROR(INDEX($AB$2:$AB$499,MATCH(LARGE($Z$2:$Z$499,1),$Z$2:$Z$499,0)),"")} -> Family | E30: {=IFERROR(INDEX($AC$2:$AC$499,MATCH(LARGE($Z$2:$Z$499,1),$Z$2:$Z$499,0)),"")} -> Transfer to Parents | F30: {=IFERROR(INDEX($AD$2:$AD$499,MATCH(LARGE($Z$2:$Z$499,1),$Z$2:$Z$499,0)),0)} -> 1000 | Z30: =IFERROR(IF(Transactions!B32="Expense",Transactions!E32+ROW()/10000000,""),"") -> 18.250003 | AA30: =IFERROR(IF(Transactions!B32="Expense",Transactions!A32,""),"") -> 46138 | AB30: =IFERROR(IF(Transactions!B32="Expense",Transactions!C32,""),"") -> Food | AC30: =IFERROR(IF(Transactions!B32="Expense",Transactions!D32,""),"") -> Mcd | AD30: =IFERROR(IF(Transactions!B32="Expense",Transactions!E32,""),"") -> 18.25
B31: 2 | C31: {=IFERROR(INDEX($AA$2:$AA$499,MATCH(LARGE($Z$2:$Z$499,2),$Z$2:$Z$499,0)),"")} -> 46155 | D31: {=IFERROR(INDEX($AB$2:$AB$499,MATCH(LARGE($Z$2:$Z$499,2),$Z$2:$Z$499,0)),"")} -> Travel | E31: {=IFERROR(INDEX($AC$2:$AC$499,MATCH(LARGE($Z$2:$Z$499,2),$Z$2:$Z$499,0)),"")} -> SGD to MYR | F31: {=IFERROR(INDEX($AD$2:$AD$499,MATCH(LARGE($Z$2:$Z$499,2),$Z$2:$Z$499,0)),0)} -> 300 | Z31: =IFERROR(IF(Transactions!B33="Expense",Transactions!E33+ROW()/10000000,""),"") | AA31: =IFERROR(IF(Transactions!B33="Expense",Transactions!A33,""),"") | AB31: =IFERROR(IF(Transactions!B33="Expense",Transactions!C33,""),"") | AC31: =IFERROR(IF(Transactions!B33="Expense",Transactions!D33,""),"") | AD31: =IFERROR(IF(Transactions!B33="Expense",Transactions!E33,""),"")
B32: 3 | C32: {=IFERROR(INDEX($AA$2:$AA$499,MATCH(LARGE($Z$2:$Z$499,3),$Z$2:$Z$499,0)),"")} -> 46148 | D32: {=IFERROR(INDEX($AB$2:$AB$499,MATCH(LARGE($Z$2:$Z$499,3),$Z$2:$Z$499,0)),"")} -> Bills | E32: {=IFERROR(INDEX($AC$2:$AC$499,MATCH(LARGE($Z$2:$Z$499,3),$Z$2:$Z$499,0)),"")} -> Tax | F32: {=IFERROR(INDEX($AD$2:$AD$499,MATCH(LARGE($Z$2:$Z$499,3),$Z$2:$Z$499,0)),0)} -> 240 | Z32: =IFERROR(IF(Transactions!B34="Expense",Transactions!E34+ROW()/10000000,""),"") -> 15.510003 | AA32: =IFERROR(IF(Transactions!B34="Expense",Transactions!A34,""),"") -> 46134 | AB32: =IFERROR(IF(Transactions!B34="Expense",Transactions!C34,""),"") -> Shopping | AC32: =IFERROR(IF(Transactions!B34="Expense",Transactions!D34,""),"") -> Shoppee | AD32: =IFERROR(IF(Transactions!B34="Expense",Transactions!E34,""),"") -> 15.51
B33: 4 | C33: {=IFERROR(INDEX($AA$2:$AA$499,MATCH(LARGE($Z$2:$Z$499,4),$Z$2:$Z$499,0)),"")} -> 46158 | D33: {=IFERROR(INDEX($AB$2:$AB$499,MATCH(LARGE($Z$2:$Z$499,4),$Z$2:$Z$499,0)),"")} -> Travel | E33: {=IFERROR(INDEX($AC$2:$AC$499,MATCH(LARGE($Z$2:$Z$499,4),$Z$2:$Z$499,0)),"")} -> KL Grand Hyatt Deposit | F33: {=IFERROR(INDEX($AD$2:$AD$499,MATCH(LARGE($Z$2:$Z$499,4),$Z$2:$Z$499,0)),0)} -> 199.45 | Z33: =IFERROR(IF(Transactions!B35="Expense",Transactions!E35+ROW()/10000000,""),"") -> 21.160003 | AA33: =IFERROR(IF(Transactions!B35="Expense",Transactions!A35,""),"") -> 46135 | AB33: =IFERROR(IF(Transactions!B35="Expense",Transactions!C35,""),"") -> Shopping | AC33: =IFERROR(IF(Transactions!B35="Expense",Transactions!D35,""),"") -> Shoppee | AD33: =IFERROR(IF(Transactions!B35="Expense",Transactions!E35,""),"") -> 21.16
B34: 5 | C34: {=IFERROR(INDEX($AA$2:$AA$499,MATCH(LARGE($Z$2:$Z$499,5),$Z$2:$Z$499,0)),"")} -> 46137 | D34: {=IFERROR(INDEX($AB$2:$AB$499,MATCH(LARGE($Z$2:$Z$499,5),$Z$2:$Z$499,0)),"")} -> Misc | E34: {=IFERROR(INDEX($AC$2:$AC$499,MATCH(LARGE($Z$2:$Z$499,5),$Z$2:$Z$499,0)),"")} -> Donation | F34: {=IFERROR(INDEX($AD$2:$AD$499,MATCH(LARGE($Z$2:$Z$499,5),$Z$2:$Z$499,0)),0)} -> 125 | Z34: =IFERROR(IF(Transactions!B36="Expense",Transactions!E36+ROW()/10000000,""),"") -> 7.0000034 | AA34: =IFERROR(IF(Transactions!B36="Expense",Transactions!A36,""),"") -> 46138 | AB34: =IFERROR(IF(Transactions!B36="Expense",Transactions!C36,""),"") -> Subscription | AC34: =IFERROR(IF(Transactions!B36="Expense",Transactions!D36,""),"") -> Gomo | AD34: =IFERROR(IF(Transactions!B36="Expense",Transactions!E36,""),"") -> 7
B35: 6 | C35: {=IFERROR(INDEX($AA$2:$AA$499,MATCH(LARGE($Z$2:$Z$499,6),$Z$2:$Z$499,0)),"")} -> 46159 | D35: {=IFERROR(INDEX($AB$2:$AB$499,MATCH(LARGE($Z$2:$Z$499,6),$Z$2:$Z$499,0)),"")} -> Shopping | E35: {=IFERROR(INDEX($AC$2:$AC$499,MATCH(LARGE($Z$2:$Z$499,6),$Z$2:$Z$499,0)),"")} -> KL Shopping | F35: {=IFERROR(INDEX($AD$2:$AD$499,MATCH(LARGE($Z$2:$Z$499,6),$Z$2:$Z$499,0)),0)} -> 116.41 | Z35: =IFERROR(IF(Transactions!B37="Expense",Transactions!E37+ROW()/10000000,""),"") -> 18.000003 | AA35: =IFERROR(IF(Transactions!B37="Expense",Transactions!A37,""),"") -> 46135 | AB35: =IFERROR(IF(Transactions!B37="Expense",Transactions!C37,""),"") -> Food | AC35: =IFERROR(IF(Transactions!B37="Expense",Transactions!D37,""),"") -> Lunch with Team | AD35: =IFERROR(IF(Transactions!B37="Expense",Transactions!E37,""),"") -> 18
B36: 7 | C36: {=IFERROR(INDEX($AA$2:$AA$499,MATCH(LARGE($Z$2:$Z$499,7),$Z$2:$Z$499,0)),"")} -> 46151 | D36: {=IFERROR(INDEX($AB$2:$AB$499,MATCH(LARGE($Z$2:$Z$499,7),$Z$2:$Z$499,0)),"")} -> Food | E36: {=IFERROR(INDEX($AC$2:$AC$499,MATCH(LARGE($Z$2:$Z$499,7),$Z$2:$Z$499,0)),"")} -> Bali Thai Mother's day | F36: {=IFERROR(INDEX($AD$2:$AD$499,MATCH(LARGE($Z$2:$Z$499,7),$Z$2:$Z$499,0)),0)} -> 109.47 | Z36: =IFERROR(IF(Transactions!B38="Expense",Transactions!E38+ROW()/10000000,""),"") | AA36: =IFERROR(IF(Transactions!B38="Expense",Transactions!A38,""),"") | AB36: =IFERROR(IF(Transactions!B38="Expense",Transactions!C38,""),"") | AC36: =IFERROR(IF(Transactions!B38="Expense",Transactions!D38,""),"") | AD36: =IFERROR(IF(Transactions!B38="Expense",Transactions!E38,""),"")
B37: 8 | C37: {=IFERROR(INDEX($AA$2:$AA$499,MATCH(LARGE($Z$2:$Z$499,8),$Z$2:$Z$499,0)),"")} -> 46143 | D37: {=IFERROR(INDEX($AB$2:$AB$499,MATCH(LARGE($Z$2:$Z$499,8),$Z$2:$Z$499,0)),"")} -> Subscription | E37: {=IFERROR(INDEX($AC$2:$AC$499,MATCH(LARGE($Z$2:$Z$499,8),$Z$2:$Z$499,0)),"")} -> Anytime Fitness | F37: {=IFERROR(INDEX($AD$2:$AD$499,MATCH(LARGE($Z$2:$Z$499,8),$Z$2:$Z$499,0)),0)} -> 89 | Z37: =IFERROR(IF(Transactions!B39="Expense",Transactions!E39+ROW()/10000000,""),"") | AA37: =IFERROR(IF(Transactions!B39="Expense",Transactions!A39,""),"") | AB37: =IFERROR(IF(Transactions!B39="Expense",Transactions!C39,""),"") | AC37: =IFERROR(IF(Transactions!B39="Expense",Transactions!D39,""),"") | AD37: =IFERROR(IF(Transactions!B39="Expense",Transactions!E39,""),"")
B38: 9 | C38: {=IFERROR(INDEX($AA$2:$AA$499,MATCH(LARGE($Z$2:$Z$499,9),$Z$2:$Z$499,0)),"")} -> 46138 | D38: {=IFERROR(INDEX($AB$2:$AB$499,MATCH(LARGE($Z$2:$Z$499,9),$Z$2:$Z$499,0)),"")} -> Subscription | E38: {=IFERROR(INDEX($AC$2:$AC$499,MATCH(LARGE($Z$2:$Z$499,9),$Z$2:$Z$499,0)),"")} -> AVG Antivirus | F38: {=IFERROR(INDEX($AD$2:$AD$499,MATCH(LARGE($Z$2:$Z$499,9),$Z$2:$Z$499,0)),0)} -> 82.62 | Z38: =IFERROR(IF(Transactions!B40="Expense",Transactions!E40+ROW()/10000000,""),"") -> 1.2000038 | AA38: =IFERROR(IF(Transactions!B40="Expense",Transactions!A40,""),"") -> 46143 | AB38: =IFERROR(IF(Transactions!B40="Expense",Transactions!C40,""),"") -> Transport | AC38: =IFERROR(IF(Transactions!B40="Expense",Transactions!D40,""),"") -> Parking | AD38: =IFERROR(IF(Transactions!B40="Expense",Transactions!E40,""),"") -> 1.2
B39: 10 | C39: {=IFERROR(INDEX($AA$2:$AA$499,MATCH(LARGE($Z$2:$Z$499,10),$Z$2:$Z$499,0)),"")} -> 46145 | D39: {=IFERROR(INDEX($AB$2:$AB$499,MATCH(LARGE($Z$2:$Z$499,10),$Z$2:$Z$499,0)),"")} -> Entertainment | E39: {=IFERROR(INDEX($AC$2:$AC$499,MATCH(LARGE($Z$2:$Z$499,10),$Z$2:$Z$499,0)),"")} -> Movie | F39: {=IFERROR(INDEX($AD$2:$AD$499,MATCH(LARGE($Z$2:$Z$499,10),$Z$2:$Z$499,0)),0)} -> 80 | Z39: =IFERROR(IF(Transactions!B41="Expense",Transactions!E41+ROW()/10000000,""),"") -> 5.8600039 | AA39: =IFERROR(IF(Transactions!B41="Expense",Transactions!A41,""),"") -> 46138 | AB39: =IFERROR(IF(Transactions!B41="Expense",Transactions!C41,""),"") -> Grocery | AC39: =IFERROR(IF(Transactions!B41="Expense",Transactions!D41,""),"") -> Fairprice | AD39: =IFERROR(IF(Transactions!B41="Expense",Transactions!E41,""),"") -> 5.86
Z40: =IFERROR(IF(Transactions!B42="Expense",Transactions!E42+ROW()/10000000,""),"") -> 7.900004 | AA40: =IFERROR(IF(Transactions!B42="Expense",Transactions!A42,""),"") -> 46139 | AB40: =IFERROR(IF(Transactions!B42="Expense",Transactions!C42,""),"") -> Food | AC40: =IFERROR(IF(Transactions!B42="Expense",Transactions!D42,""),"") -> Wokhey | AD40: =IFERROR(IF(Transactions!B42="Expense",Transactions!E42,""),"") -> 7.9
B41: 4. Subscription Spending Total | Z41: =IFERROR(IF(Transactions!B43="Expense",Transactions!E43+ROW()/10000000,""),"") -> 0.1700041 | AA41: =IFERROR(IF(Transactions!B43="Expense",Transactions!A43,""),"") -> 46139 | AB41: =IFERROR(IF(Transactions!B43="Expense",Transactions!C43,""),"") -> Food | AC41: =IFERROR(IF(Transactions!B43="Expense",Transactions!D43,""),"") | AD41: =IFERROR(IF(Transactions!B43="Expense",Transactions!E43,""),"") -> 0.17
B42: Metric | C42: Value | Z42: =IFERROR(IF(Transactions!B44="Expense",Transactions!E44+ROW()/10000000,""),"") -> 7.8000042 | AA42: =IFERROR(IF(Transactions!B44="Expense",Transactions!A44,""),"") -> 46140 | AB42: =IFERROR(IF(Transactions!B44="Expense",Transactions!C44,""),"") -> Food | AC42: =IFERROR(IF(Transactions!B44="Expense",Transactions!D44,""),"") -> Citi Cafe | AD42: =IFERROR(IF(Transactions!B44="Expense",Transactions!E44,""),"") -> 7.8
B43: Total spent on Subscriptions (all-time) | C43: =SUMIFS(Transactions!E:E,Transactions!B:B,"Expense",Transactions!C:C,"Subscription") -> 437.369 | Z43: =IFERROR(IF(Transactions!B45="Expense",Transactions!E45+ROW()/10000000,""),"") -> 0.1000043 | AA43: =IFERROR(IF(Transactions!B45="Expense",Transactions!A45,""),"") -> 46140 | AB43: =IFERROR(IF(Transactions!B45="Expense",Transactions!C45,""),"") -> Transport | AC43: =IFERROR(IF(Transactions!B45="Expense",Transactions!D45,""),"") -> Bus | AD43: =IFERROR(IF(Transactions!B45="Expense",Transactions!E45,""),"") -> 0.1
B44: # of Subscription charges | C44: =COUNTIFS(Transactions!B:B,"Expense",Transactions!C:C,"Subscription") -> 18 | Z44: =IFERROR(IF(Transactions!B46="Expense",Transactions!E46+ROW()/10000000,""),"") -> 11.500004 | AA44: =IFERROR(IF(Transactions!B46="Expense",Transactions!A46,""),"") -> 46141 | AB44: =IFERROR(IF(Transactions!B46="Expense",Transactions!C46,""),"") -> Food | AC44: =IFERROR(IF(Transactions!B46="Expense",Transactions!D46,""),"") -> Stuffd | AD44: =IFERROR(IF(Transactions!B46="Expense",Transactions!E46,""),"") -> 11.5
B45: Avg Subscription charge | C45: =IFERROR(C43/C44,0) -> 24.298278 | Z45: =IFERROR(IF(Transactions!B47="Expense",Transactions!E47+ROW()/10000000,""),"") -> 14.500004 | AA45: =IFERROR(IF(Transactions!B47="Expense",Transactions!A47,""),"") -> 46142 | AB45: =IFERROR(IF(Transactions!B47="Expense",Transactions!C47,""),"") -> Food | AC45: =IFERROR(IF(Transactions!B47="Expense",Transactions!D47,""),"") -> Andes | AD45: =IFERROR(IF(Transactions!B47="Expense",Transactions!E47,""),"") -> 14.5
B46: Projected annual subscription cost | C46: =C45*12 -> 291.57933 | Z46: =IFERROR(IF(Transactions!B48="Expense",Transactions!E48+ROW()/10000000,""),"") -> 26.480005 | AA46: =IFERROR(IF(Transactions!B48="Expense",Transactions!A48,""),"") -> 46143 | AB46: =IFERROR(IF(Transactions!B48="Expense",Transactions!C48,""),"") -> Shopping | AC46: =IFERROR(IF(Transactions!B48="Expense",Transactions!D48,""),"") -> Arenaclub Pokemon Slab | AD46: =IFERROR(IF(Transactions!B48="Expense",Transactions!E48,""),"") -> 26.48
Z47: =IFERROR(IF(Transactions!B49="Expense",Transactions!E49+ROW()/10000000,""),"") -> 89.000005 | AA47: =IFERROR(IF(Transactions!B49="Expense",Transactions!A49,""),"") -> 46143 | AB47: =IFERROR(IF(Transactions!B49="Expense",Transactions!C49,""),"") -> Subscription | AC47: =IFERROR(IF(Transactions!B49="Expense",Transactions!D49,""),"") -> Anytime Fitness | AD47: =IFERROR(IF(Transactions!B49="Expense",Transactions!E49,""),"") -> 89
B48: 5. Months Where Spending Exceeded Income | Z48: =IFERROR(IF(Transactions!B50="Expense",Transactions!E50+ROW()/10000000,""),"") -> 75.000005 | AA48: =IFERROR(IF(Transactions!B50="Expense",Transactions!A50,""),"") -> 46143 | AB48: =IFERROR(IF(Transactions!B50="Expense",Transactions!C50,""),"") -> Food | AC48: =IFERROR(IF(Transactions!B50="Expense",Transactions!D50,""),"") -> DTF + Movie | AD48: =IFERROR(IF(Transactions!B50="Expense",Transactions!E50,""),"") -> 75
B49: Month | C49: Income | D49: Expense | E49: Overspend | F49: Status | Z49: =IFERROR(IF(Transactions!B51="Expense",Transactions!E51+ROW()/10000000,""),"") -> 39.900005 | AA49: =IFERROR(IF(Transactions!B51="Expense",Transactions!A51,""),"") -> 46144 | AB49: =IFERROR(IF(Transactions!B51="Expense",Transactions!C51,""),"") -> Shopping | AC49: =IFERROR(IF(Transactions!B51="Expense",Transactions!D51,""),"") -> Pokemon Card | AD49: =IFERROR(IF(Transactions!B51="Expense",Transactions!E51,""),"") -> 39.9
B50: Feb 2026 | C50: =#REF! -> #REF! | D50: =#REF! -> #REF! | E50: =MAX(D50-C50,0) -> #REF! | F50: =IF(D50>C50,"⚠ Over Budget","OK") -> #REF! | Z50: =IFERROR(IF(Transactions!B52="Expense",Transactions!E52+ROW()/10000000,""),"") -> 30.000005 | AA50: =IFERROR(IF(Transactions!B52="Expense",Transactions!A52,""),"") -> 46144 | AB50: =IFERROR(IF(Transactions!B52="Expense",Transactions!C52,""),"") -> Subscription | AC50: =IFERROR(IF(Transactions!B52="Expense",Transactions!D52,""),"") -> Claude | AD50: =IFERROR(IF(Transactions!B52="Expense",Transactions!E52,""),"") -> 30
B51: Mar 2026 | C51: =#REF! -> #REF! | D51: =#REF! -> #REF! | E51: =MAX(D51-C51,0) -> #REF! | F51: =IF(D51>C51,"⚠ Over Budget","OK") -> #REF! | Z51: =IFERROR(IF(Transactions!B53="Expense",Transactions!E53+ROW()/10000000,""),"") -> 4.8000051 | AA51: =IFERROR(IF(Transactions!B53="Expense",Transactions!A53,""),"") -> 46143 | AB51: =IFERROR(IF(Transactions!B53="Expense",Transactions!C53,""),"") -> Food | AC51: =IFERROR(IF(Transactions!B53="Expense",Transactions!D53,""),"") -> Drinks | AD51: =IFERROR(IF(Transactions!B53="Expense",Transactions!E53,""),"") -> 4.8
B52: Apr 2026 | C52: =C7 -> 8681.09 | D52: =D7 -> 590.359 | E52: =MAX(D52-C52,0) -> 0 | F52: =IF(D52>C52,"⚠ Over Budget","OK") -> OK | Z52: =IFERROR(IF(Transactions!B54="Expense",Transactions!E54+ROW()/10000000,""),"") -> 6.1000052 | AA52: =IFERROR(IF(Transactions!B54="Expense",Transactions!A54,""),"") -> 46143 | AB52: =IFERROR(IF(Transactions!B54="Expense",Transactions!C54,""),"") -> Food | AC52: =IFERROR(IF(Transactions!B54="Expense",Transactions!D54,""),"") -> Breadtalk | AD52: =IFERROR(IF(Transactions!B54="Expense",Transactions!E54,""),"") -> 6.1
B53: May 2026 | C53: =C8 -> 6776.5 | D53: =D8 -> 3776.96 | E53: =MAX(D53-C53,0) -> 0 | F53: =IF(D53>C53,"⚠ Over Budget","OK") -> OK | Z53: =IFERROR(IF(Transactions!B55="Expense",Transactions!E55+ROW()/10000000,""),"") -> 6.5000053 | AA53: =IFERROR(IF(Transactions!B55="Expense",Transactions!A55,""),"") -> 46144 | AB53: =IFERROR(IF(Transactions!B55="Expense",Transactions!C55,""),"") -> Food | AC53: =IFERROR(IF(Transactions!B55="Expense",Transactions!D55,""),"") -> BK | AD53: =IFERROR(IF(Transactions!B55="Expense",Transactions!E55,""),"") -> 6.5
B54: Jun 2026 | C54: =C9 -> 0 | D54: =D9 -> 0 | E54: =MAX(D54-C54,0) -> 0 | F54: =IF(D54>C54,"⚠ Over Budget","OK") -> OK | Z54: =IFERROR(IF(Transactions!B56="Expense",Transactions!E56+ROW()/10000000,""),"") -> 13.450005 | AA54: =IFERROR(IF(Transactions!B56="Expense",Transactions!A56,""),"") -> 46144 | AB54: =IFERROR(IF(Transactions!B56="Expense",Transactions!C56,""),"") -> Subscription | AC54: =IFERROR(IF(Transactions!B56="Expense",Transactions!D56,""),"") -> Hetzener VPS | AD54: =IFERROR(IF(Transactions!B56="Expense",Transactions!E56,""),"") -> 13.45
B55: Jul 2026 | C55: =C10 -> 0 | D55: =D10 -> 0 | E55: =MAX(D55-C55,0) -> 0 | F55: =IF(D55>C55,"⚠ Over Budget","OK") -> OK | Z55: =IFERROR(IF(Transactions!B57="Expense",Transactions!E57+ROW()/10000000,""),"") -> 33.900005 | AA55: =IFERROR(IF(Transactions!B57="Expense",Transactions!A57,""),"") -> 46144 | AB55: =IFERROR(IF(Transactions!B57="Expense",Transactions!C57,""),"") -> Subscription | AC55: =IFERROR(IF(Transactions!B57="Expense",Transactions!D57,""),"") -> Newspaper | AD55: =IFERROR(IF(Transactions!B57="Expense",Transactions!E57,""),"") -> 33.9
Z56: =IFERROR(IF(Transactions!B58="Expense",Transactions!E58+ROW()/10000000,""),"") -> 80.000006 | AA56: =IFERROR(IF(Transactions!B58="Expense",Transactions!A58,""),"") -> 46145 | AB56: =IFERROR(IF(Transactions!B58="Expense",Transactions!C58,""),"") -> Entertainment | AC56: =IFERROR(IF(Transactions!B58="Expense",Transactions!D58,""),"") -> Movie | AD56: =IFERROR(IF(Transactions!B58="Expense",Transactions!E58,""),"") -> 80
B57: 6. Savings Opportunities (Top 3 Categories) | Z57: =IFERROR(IF(Transactions!B59="Expense",Transactions!E59+ROW()/10000000,""),"") -> 14.000006 | AA57: =IFERROR(IF(Transactions!B59="Expense",Transactions!A59,""),"") -> 46145 | AB57: =IFERROR(IF(Transactions!B59="Expense",Transactions!C59,""),"") -> Transport | AC57: =IFERROR(IF(Transactions!B59="Expense",Transactions!D59,""),"") -> Car Wash | AD57: =IFERROR(IF(Transactions!B59="Expense",Transactions!E59,""),"") -> 14
B58: Rank | C58: Category | D58: Current Spend | E58: Cut 10% | F58: Cut 20% | Z58: =IFERROR(IF(Transactions!B60="Expense",Transactions!E60+ROW()/10000000,""),"") -> 3.4000058 | AA58: =IFERROR(IF(Transactions!B60="Expense",Transactions!A60,""),"") -> 46146 | AB58: =IFERROR(IF(Transactions!B60="Expense",Transactions!C60,""),"") -> Food | AC58: =IFERROR(IF(Transactions!B60="Expense",Transactions!D60,""),"") -> Tea | AD58: =IFERROR(IF(Transactions!B60="Expense",Transactions!E60,""),"") -> 3.4
B59: 1 | C59: {=IFERROR(INDEX(Dashboard!$J$22:$J$32,MATCH(LARGE(Dashboard!$K$22:$K$32,1),Dashboard!$K$22:$K$32,0)),"")} -> Family | D59: =IFERROR(LARGE(Dashboard!$K$22:$K$32,1),0) -> 1000 | E59: =D59*0.1 -> 100 | F59: =D59*0.2 -> 200 | Z59: =IFERROR(IF(Transactions!B61="Expense",Transactions!E61+ROW()/10000000,""),"") -> 8.5000059 | AA59: =IFERROR(IF(Transactions!B61="Expense",Transactions!A61,""),"") -> 46147 | AB59: =IFERROR(IF(Transactions!B61="Expense",Transactions!C61,""),"") -> Food | AC59: =IFERROR(IF(Transactions!B61="Expense",Transactions!D61,""),"") -> Citi Cafe | AD59: =IFERROR(IF(Transactions!B61="Expense",Transactions!E61,""),"") -> 8.5
B60: 2 | C60: {=IFERROR(INDEX(Dashboard!$J$22:$J$32,MATCH(LARGE(Dashboard!$K$22:$K$32,2),Dashboard!$K$22:$K$32,0)),"")} -> Food | D60: =IFERROR(LARGE(Dashboard!$K$22:$K$32,2),0) -> 847.14 | E60: =D60*0.1 -> 84.714 | F60: =D60*0.2 -> 169.428 | Z60: =IFERROR(IF(Transactions!B62="Expense",Transactions!E62+ROW()/10000000,""),"") -> 240.00001 | AA60: =IFERROR(IF(Transactions!B62="Expense",Transactions!A62,""),"") -> 46148 | AB60: =IFERROR(IF(Transactions!B62="Expense",Transactions!C62,""),"") -> Bills | AC60: =IFERROR(IF(Transactions!B62="Expense",Transactions!D62,""),"") -> Tax | AD60: =IFERROR(IF(Transactions!B62="Expense",Transactions!E62,""),"") -> 240
B61: 3 | C61: {=IFERROR(INDEX(Dashboard!$J$22:$J$32,MATCH(LARGE(Dashboard!$K$22:$K$32,3),Dashboard!$K$22:$K$32,0)),"")} -> Travel | D61: =IFERROR(LARGE(Dashboard!$K$22:$K$32,3),0) -> 563.95 | E61: =D61*0.1 -> 56.395 | F61: =D61*0.2 -> 112.79 | Z61: =IFERROR(IF(Transactions!B63="Expense",Transactions!E63+ROW()/10000000,""),"") -> 13.000006 | AA61: =IFERROR(IF(Transactions!B63="Expense",Transactions!A63,""),"") -> 46148 | AB61: =IFERROR(IF(Transactions!B63="Expense",Transactions!C63,""),"") -> Transport | AC61: =IFERROR(IF(Transactions!B63="Expense",Transactions!D63,""),"") -> Grab Taxi | AD61: =IFERROR(IF(Transactions!B63="Expense",Transactions!E63,""),"") -> 13
Z62: =IFERROR(IF(Transactions!B64="Expense",Transactions!E64+ROW()/10000000,""),"") | AA62: =IFERROR(IF(Transactions!B64="Expense",Transactions!A64,""),"") | AB62: =IFERROR(IF(Transactions!B64="Expense",Transactions!C64,""),"") | AC62: =IFERROR(IF(Transactions!B64="Expense",Transactions!D64,""),"") | AD62: =IFERROR(IF(Transactions!B64="Expense",Transactions!E64,""),"")
B63: Tip: cutting 20% across the top 3 categories above = potential monthly savings below. | Z63: =IFERROR(IF(Transactions!B65="Expense",Transactions!E65+ROW()/10000000,""),"") | AA63: =IFERROR(IF(Transactions!B65="Expense",Transactions!A65,""),"") | AB63: =IFERROR(IF(Transactions!B65="Expense",Transactions!C65,""),"") | AC63: =IFERROR(IF(Transactions!B65="Expense",Transactions!D65,""),"") | AD63: =IFERROR(IF(Transactions!B65="Expense",Transactions!E65,""),"")
B64: Estimated monthly savings | C64: =SUM(F59:F61)/COUNT(Dashboard!$K$13:$K$18) -> 80.369667 | Z64: =IFERROR(IF(Transactions!B66="Expense",Transactions!E66+ROW()/10000000,""),"") | AA64: =IFERROR(IF(Transactions!B66="Expense",Transactions!A66,""),"") | AB64: =IFERROR(IF(Transactions!B66="Expense",Transactions!C66,""),"") | AC64: =IFERROR(IF(Transactions!B66="Expense",Transactions!D66,""),"") | AD64: =IFERROR(IF(Transactions!B66="Expense",Transactions!E66,""),"")
Z65: =IFERROR(IF(Transactions!B67="Expense",Transactions!E67+ROW()/10000000,""),"") -> 28.590007 | AA65: =IFERROR(IF(Transactions!B67="Expense",Transactions!A67,""),"") -> 46151 | AB65: =IFERROR(IF(Transactions!B67="Expense",Transactions!C67,""),"") -> Subscription | AC65: =IFERROR(IF(Transactions!B67="Expense",Transactions!D67,""),"") -> ChatGPT | AD65: =IFERROR(IF(Transactions!B67="Expense",Transactions!E67,""),"") -> 28.59
Z66: =IFERROR(IF(Transactions!B68="Expense",Transactions!E68+ROW()/10000000,""),"") -> 19.900007 | AA66: =IFERROR(IF(Transactions!B68="Expense",Transactions!A68,""),"") -> 46145 | AB66: =IFERROR(IF(Transactions!B68="Expense",Transactions!C68,""),"") -> Shopping | AC66: =IFERROR(IF(Transactions!B68="Expense",Transactions!D68,""),"") -> Pokemon Card | AD66: =IFERROR(IF(Transactions!B68="Expense",Transactions!E68,""),"") -> 19.9
Z67: =IFERROR(IF(Transactions!B69="Expense",Transactions!E69+ROW()/10000000,""),"") -> 15.960007 | AA67: =IFERROR(IF(Transactions!B69="Expense",Transactions!A69,""),"") -> 46145 | AB67: =IFERROR(IF(Transactions!B69="Expense",Transactions!C69,""),"") -> Shopping | AC67: =IFERROR(IF(Transactions!B69="Expense",Transactions!D69,""),"") -> Pokemon Card | AD67: =IFERROR(IF(Transactions!B69="Expense",Transactions!E69,""),"") -> 15.96
Z68: =IFERROR(IF(Transactions!B70="Expense",Transactions!E70+ROW()/10000000,""),"") -> 70.000007 | AA68: =IFERROR(IF(Transactions!B70="Expense",Transactions!A70,""),"") -> 46146 | AB68: =IFERROR(IF(Transactions!B70="Expense",Transactions!C70,""),"") -> Misc | AC68: =IFERROR(IF(Transactions!B70="Expense",Transactions!D70,""),"") -> Donation | AD68: =IFERROR(IF(Transactions!B70="Expense",Transactions!E70,""),"") -> 70
Z69: =IFERROR(IF(Transactions!B71="Expense",Transactions!E71+ROW()/10000000,""),"") -> 9.0000069 | AA69: =IFERROR(IF(Transactions!B71="Expense",Transactions!A71,""),"") -> 46148 | AB69: =IFERROR(IF(Transactions!B71="Expense",Transactions!C71,""),"") -> Subscription | AC69: =IFERROR(IF(Transactions!B71="Expense",Transactions!D71,""),"") -> NTUC membership | AD69: =IFERROR(IF(Transactions!B71="Expense",Transactions!E71,""),"") -> 9
Z70: =IFERROR(IF(Transactions!B72="Expense",Transactions!E72+ROW()/10000000,""),"") -> 20.000007 | AA70: =IFERROR(IF(Transactions!B72="Expense",Transactions!A72,""),"") -> 46145 | AB70: =IFERROR(IF(Transactions!B72="Expense",Transactions!C72,""),"") -> Food | AC70: =IFERROR(IF(Transactions!B72="Expense",Transactions!D72,""),"") -> Popcorn | AD70: =IFERROR(IF(Transactions!B72="Expense",Transactions!E72,""),"") -> 20
Z71: =IFERROR(IF(Transactions!B73="Expense",Transactions!E73+ROW()/10000000,""),"") -> 23.650007 | AA71: =IFERROR(IF(Transactions!B73="Expense",Transactions!A73,""),"") -> 46146 | AB71: =IFERROR(IF(Transactions!B73="Expense",Transactions!C73,""),"") -> Grocery | AC71: =IFERROR(IF(Transactions!B73="Expense",Transactions!D73,""),"") -> Fairprice | AD71: =IFERROR(IF(Transactions!B73="Expense",Transactions!E73,""),"") -> 23.65
Z72: =IFERROR(IF(Transactions!B74="Expense",Transactions!E74+ROW()/10000000,""),"") -> 11.900007 | AA72: =IFERROR(IF(Transactions!B74="Expense",Transactions!A74,""),"") -> 46146 | AB72: =IFERROR(IF(Transactions!B74="Expense",Transactions!C74,""),"") -> Food | AC72: =IFERROR(IF(Transactions!B74="Expense",Transactions!D74,""),"") -> Burger King | AD72: =IFERROR(IF(Transactions!B74="Expense",Transactions!E74,""),"") -> 11.9
Z73: =IFERROR(IF(Transactions!B75="Expense",Transactions!E75+ROW()/10000000,""),"") -> 7.1000073 | AA73: =IFERROR(IF(Transactions!B75="Expense",Transactions!A75,""),"") -> 46148 | AB73: =IFERROR(IF(Transactions!B75="Expense",Transactions!C75,""),"") -> Food | AC73: =IFERROR(IF(Transactions!B75="Expense",Transactions!D75,""),"") -> Chicken Rice | AD73: =IFERROR(IF(Transactions!B75="Expense",Transactions!E75,""),"") -> 7.1
Z74: =IFERROR(IF(Transactions!B76="Expense",Transactions!E76+ROW()/10000000,""),"") -> 7.1000074 | AA74: =IFERROR(IF(Transactions!B76="Expense",Transactions!A76,""),"") -> 46149 | AB74: =IFERROR(IF(Transactions!B76="Expense",Transactions!C76,""),"") -> Food | AC74: =IFERROR(IF(Transactions!B76="Expense",Transactions!D76,""),"") -> Chicken Rice | AD74: =IFERROR(IF(Transactions!B76="Expense",Transactions!E76,""),"") -> 7.1
Z75: =IFERROR(IF(Transactions!B77="Expense",Transactions!E77+ROW()/10000000,""),"") -> 7.1000075 | AA75: =IFERROR(IF(Transactions!B77="Expense",Transactions!A77,""),"") -> 46150 | AB75: =IFERROR(IF(Transactions!B77="Expense",Transactions!C77,""),"") -> Food | AC75: =IFERROR(IF(Transactions!B77="Expense",Transactions!D77,""),"") -> Chicken Rice | AD75: =IFERROR(IF(Transactions!B77="Expense",Transactions!E77,""),"") -> 7.1
Z76: =IFERROR(IF(Transactions!B78="Expense",Transactions!E78+ROW()/10000000,""),"") -> 28.280008 | AA76: =IFERROR(IF(Transactions!B78="Expense",Transactions!A78,""),"") -> 46151 | AB76: =IFERROR(IF(Transactions!B78="Expense",Transactions!C78,""),"") -> Shopping | AC76: =IFERROR(IF(Transactions!B78="Expense",Transactions!D78,""),"") -> Nasal Strip | AD76: =IFERROR(IF(Transactions!B78="Expense",Transactions!E78,""),"") -> 28.28
... Z90: =IFERROR(IF(Transactions!B92="Expense",Transactions!E92+ROW()/10000000,""),"") -> 2.000009 | AA90: =IFERROR(IF(Transactions!B92="Expense",Transactions!A92,""),"") -> 46153 | AB90: =IFERROR(IF(Transactions!B92="Expense",Transactions!C92,""),"") -> Misc | AC90: =IFERROR(IF(Transactions!B92="Expense",Transactions!D92,""),"") -> Toto | AD90: =IFERROR(IF(Transactions!B92="Expense",Transactions!E92,""),"") -> 2
Z91: =IFERROR(IF(Transactions!B93="Expense",Transactions!E93+ROW()/10000000,""),"") -> 22.980009 | AA91: =IFERROR(IF(Transactions!B93="Expense",#REF!,""),"") | AB91: =IFERROR(IF(Transactions!B93="Expense",Transactions!C93,""),"") -> Subscription | AC91: =IFERROR(IF(Transactions!B93="Expense",Transactions!D93,""),"") -> Netflix | AD91: =IFERROR(IF(Transactions!B93="Expense",Transactions!E93,""),"") -> 22.98
Z92: =IFERROR(IF(Transactions!B94="Expense",Transactions!E94+ROW()/10000000,""),"") -> 300.00001 | AA92: =IFERROR(IF(Transactions!B94="Expense",Transactions!A93,""),"") -> 46155 | AB92: =IFERROR(IF(Transactions!B94="Expense",Transactions!C94,""),"") -> Travel | AC92: =IFERROR(IF(Transactions!B94="Expense",Transactions!D94,""),"") -> SGD to MYR | AD92: =IFERROR(IF(Transactions!B94="Expense",Transactions!E94,""),"") -> 300
Z93: =IFERROR(IF(Transactions!B95="Expense",Transactions!E95+ROW()/10000000,""),"") -> 17.460009 | AA93: =IFERROR(IF(Transactions!B95="Expense",Transactions!A95,""),"") -> 46159 | AB93: =IFERROR(IF(Transactions!B95="Expense",Transactions!C95,""),"") -> Subscription | AC93: =IFERROR(IF(Transactions!B95="Expense",Transactions!D95,""),"") -> Spotify | AD93: =IFERROR(IF(Transactions!B95="Expense",Transactions!E95,""),"") -> 17.46
Z94: =IFERROR(IF(Transactions!B96="Expense",Transactions!E96+ROW()/10000000,""),"") -> 7.0000094 | AA94: =IFERROR(IF(Transactions!B96="Expense",Transactions!A96,""),"") -> 46162 | AB94: =IFERROR(IF(Transactions!B96="Expense",Transactions!C96,""),"") -> Food | AC94: =IFERROR(IF(Transactions!B96="Expense",Transactions!D96,""),"") -> Mixed Rice | AD94: =IFERROR(IF(Transactions!B96="Expense",Transactions!E96,""),"") -> 7
Z95: =IFERROR(IF(Transactions!B97="Expense",Transactions!E97+ROW()/10000000,""),"") -> 10.380009 | AA95: =IFERROR(IF(Transactions!B97="Expense",Transactions!A97,""),"") -> 46152 | AB95: =IFERROR(IF(Transactions!B97="Expense",Transactions!C97,""),"") -> Transport | AC95: =IFERROR(IF(Transactions!B97="Expense",Transactions!D97,""),"") -> MRT | AD95: =IFERROR(IF(Transactions!B97="Expense",Transactions!E97,""),"") -> 10.38
Z96: =IFERROR(IF(Transactions!B98="Expense",Transactions!E98+ROW()/10000000,""),"") -> 4.5000096 | AA96: =IFERROR(IF(Transactions!B98="Expense",Transactions!A98,""),"") -> 46157 | AB96: =IFERROR(IF(Transactions!B98="Expense",Transactions!C98,""),"") -> Food | AC96: =IFERROR(IF(Transactions!B98="Expense",Transactions!D98,""),"") -> Koufu | AD96: =IFERROR(IF(Transactions!B98="Expense",Transactions!E98,""),"") -> 4.5
Z97: =IFERROR(IF(Transactions!B99="Expense",Transactions!E99+ROW()/10000000,""),"") -> 18.20001 | AA97: =IFERROR(IF(Transactions!B99="Expense",Transactions!A99,""),"") -> 46157 | AB97: =IFERROR(IF(Transactions!B99="Expense",Transactions!C99,""),"") -> Food | AC97: =IFERROR(IF(Transactions!B99="Expense",Transactions!D99,""),"") -> Mcd | AD97: =IFERROR(IF(Transactions!B99="Expense",Transactions!E99,""),"") -> 18.2
Z98: =IFERROR(IF(Transactions!B100="Expense",Transactions!E100+ROW()/10000000,""),"") -> 19.00001 | AA98: =IFERROR(IF(Transactions!B100="Expense",Transactions!A100,""),"") -> 46157 | AB98: =IFERROR(IF(Transactions!B100="Expense",Transactions!C100,""),"") -> Shopping | AC98: =IFERROR(IF(Transactions!B100="Expense",Transactions!D100,""),"") -> Mustafa | AD98: =IFERROR(IF(Transactions!B100="Expense",Transactions!E100,""),"") -> 19
Z99: =IFERROR(IF(Transactions!B101="Expense",Transactions!E101+ROW()/10000000,""),"") -> 31.50001 | AA99: =IFERROR(IF(Transactions!B101="Expense",Transactions!A101,""),"") -> 46157 | AB99: =IFERROR(IF(Transactions!B101="Expense",Transactions!C101,""),"") -> Travel | AC99: =IFERROR(IF(Transactions!B101="Expense",Transactions!D101,""),"") -> KL Express train | AD99: =IFERROR(IF(Transactions!B101="Expense",Transactions!E101,""),"") -> 31.5
Z100: =IFERROR(IF(Transactions!B102="Expense",Transactions!E102+ROW()/10000000,""),"") -> 16.00001 | AA100: =IFERROR(IF(Transactions!B102="Expense",Transactions!A102,""),"") -> 46158 | AB100: =IFERROR(IF(Transactions!B102="Expense",Transactions!C102,""),"") -> Food | AC100: =IFERROR(IF(Transactions!B102="Expense",Transactions!D102,""),"") -> Boost | AD100: =IFERROR(IF(Transactions!B102="Expense",Transactions!E102,""),"") -> 16
Z101: =IFERROR(IF(Transactions!B103="Expense",Transactions!E103+ROW()/10000000,""),"") -> 13.98001 | AA101: =IFERROR(IF(Transactions!B103="Expense",Transactions!A103,""),"") -> 46160 | AB101: =IFERROR(IF(Transactions!B103="Expense",Transactions!C103,""),"") -> Subscription | AC101: =IFERROR(IF(Transactions!B103="Expense",Transactions!D103,""),"") -> iCloud | AD101: =IFERROR(IF(Transactions!B103="Expense",Transactions!E103,""),"") -> 13.98
Z102: =IFERROR(IF(Transactions!B104="Expense",Transactions!E104+ROW()/10000000,""),"") -> 31.20001 | AA102: =IFERROR(IF(Transactions!B104="Expense",Transactions!A104,""),"") -> 46160 | AB102: =IFERROR(IF(Transactions!B104="Expense",Transactions!C104,""),"") -> Travel | AC102: =IFERROR(IF(Transactions!B104="Expense",Transactions!D104,""),"") -> KL Express train | AD102: =IFERROR(IF(Transactions!B104="Expense",Transactions!E104,""),"") -> 31.2
Z103: =IFERROR(IF(Transactions!B105="Expense",Transactions!E105+ROW()/10000000,""),"") -> 6.1000103 | AA103: =IFERROR(IF(Transactions!B105="Expense",Transactions!A105,""),"") -> 46161 | AB103: =IFERROR(IF(Transactions!B105="Expense",Transactions!C105,""),"") -> Food | AC103: =IFERROR(IF(Transactions!B105="Expense",Transactions!D105,""),"") -> Chicken Rice | AD103: =IFERROR(IF(Transactions!B105="Expense",Transactions!E105,""),"") -> 6.1
Z104: =IFERROR(IF(Transactions!B106="Expense",Transactions!E106+ROW()/10000000,""),"") -> 2.7000104 | AA104: =IFERROR(IF(Transactions!B106="Expense",Transactions!A106,""),"") -> 46161 | AB104: =IFERROR(IF(Transactions!B106="Expense",Transactions!C106,""),"") -> Food | AC104: =IFERROR(IF(Transactions!B106="Expense",Transactions!D106,""),"") -> Siew Mai | AD104: =IFERROR(IF(Transactions!B106="Expense",Transactions!E106,""),"") -> 2.7
... Z499: =IFERROR(IF(Transactions!B501="Expense",Transactions!E501+ROW()/10000000,""),"") | AA499: =IFERROR(IF(Transactions!B501="Expense",Transactions!A501,""),"") | AB499: =IFERROR(IF(Transactions!B501="Expense",Transactions!C501,""),"") | AC499: =IFERROR(IF(Transactions!B501="Expense",Transactions!D501,""),"") | AD499: =IFERROR(IF(Transactions!B501="Expense",Transactions!E501,""),"")
